Topsis_Apurvi_101953006/__init__.py
Topsis_Apurvi_101953006/topsis.py
Topsis_Apurvi_101953006-0.0.2.dist-info/LICENSE
Topsis_Apurvi_101953006-0.0.2.dist-info/METADATA
Topsis_Apurvi_101953006-0.0.2.dist-info/WHEEL
Topsis_Apurvi_101953006-0.0.2.dist-info/entry_points.txt
Topsis_Apurvi_101953006-0.0.2.dist-info/top_level.txt
Topsis_Apurvi_101953006-0.0.2.dist-info/RECORD
